odoo/addons/widget_list_message/README.rst
odoo/addons/widget_list_message/__init__.py
odoo/addons/widget_list_message/__manifest__.py
odoo/addons/widget_list_message/static/description/icon.png
odoo/addons/widget_list_message/static/src/js/list_renderer.js
odoo/addons/widget_list_message/views/widget_list_message_view.xml
odoo12_addon_widget_list_message-12.0.0.1.0.dist-info/METADATA
odoo12_addon_widget_list_message-12.0.0.1.0.dist-info/WHEEL
odoo12_addon_widget_list_message-12.0.0.1.0.dist-info/top_level.txt
odoo12_addon_widget_list_message-12.0.0.1.0.dist-info/RECORD
